isatools/__init__.py
isatools/__main__.py
isatools/constants.py
isatools/logging.py
isatools/magetab.py
isatools/sampletab.py
isatools/sra.py
isatools/utils.py
isatools/convert/__init__.py
isatools/convert/isatab2cedar.py
isatools/convert/isatab2json.py
isatools/convert/isatab2magetab.py
isatools/convert/isatab2sampletab.py
isatools/convert/isatab2sra.py
isatools/convert/isatab2w4m.py
isatools/convert/json2isatab.py
isatools/convert/json2magetab.py
isatools/convert/json2sampletab.py
isatools/convert/json2sra.py
isatools/convert/magetab2isatab.py
isatools/convert/magetab2json.py
isatools/convert/mzml2isa.py
isatools/convert/sampletab2isatab.py
isatools/convert/sampletab2json.py
isatools/create/__init__.py
isatools/create/assay_templates.py
isatools/create/connectors.py
isatools/create/constants.py
isatools/create/errors.py
isatools/create/model.py
isatools/database/__init__.py
isatools/database/utils.py
isatools/database/models/__init__.py
isatools/database/models/assay.py
isatools/database/models/characteristic.py
isatools/database/models/comment.py
isatools/database/models/constraints.py
isatools/database/models/datafile.py
isatools/database/models/factor_value.py
isatools/database/models/inputs_outputs.py
isatools/database/models/investigation.py
isatools/database/models/material.py
isatools/database/models/ontology_annotation.py
isatools/database/models/ontology_source.py
isatools/database/models/parameter.py
isatools/database/models/parameter_value.py
isatools/database/models/person.py
isatools/database/models/process.py
isatools/database/models/protocol.py
isatools/database/models/publication.py
isatools/database/models/relationships.py
isatools/database/models/sample.py
isatools/database/models/source.py
isatools/database/models/study.py
isatools/database/models/study_factor.py
isatools/database/models/utils.py
isatools/graphQL/README.md
isatools/graphQL/custom_scalars.py
isatools/graphQL/inputs.py
isatools/graphQL/models.py
isatools/graphQL/unions.py
isatools-0.14.2.dist-info/LICENSE.txt
isatools-0.14.2.dist-info/METADATA
isatools-0.14.2.dist-info/WHEEL
isatools-0.14.2.dist-info/top_level.txt
isatools-0.14.2.dist-info/RECORD
