Metadata-Version: 2.1
Name: isatools
Version: 0.14.2
Summary: Metadata tracking tools help to manage an increasingly diverse set of life science, environmental and biomedical experiments
Home-page: https://github.com/ISA-tools/isa-api
Author: ISA Infrastructure Team
Author-email: isatools@googlegroups.com
Classifier: Development Status :: 5 - Production/Stable
Classifier: Intended Audience :: Science/Research
Classifier: Intended Audience :: Developers
Classifier: Intended Audience :: System Administrators
Classifier: Topic :: Scientific/Engineering :: Bio-Informatics
Classifier: Programming Language :: Python :: 3.8
Classifier: Programming Language :: Python :: 3.9
Classifier: Programming Language :: Python :: 3.10
License-File: LICENSE.txt
Requires-Dist: graphene (==3.1.1)
Requires-Dist: graphql-core (==3.2.3)
Requires-Dist: wheel (~=0.36.2)
Requires-Dist: setuptools (~=57.1.0)
Requires-Dist: numpy (~=1.23.3)
Requires-Dist: jsonschema (~=3.2.0)
Requires-Dist: pandas (==1.5.0)
Requires-Dist: openpyxl (>=2.5.0)
Requires-Dist: networkx (~=2.5.1)
Requires-Dist: lxml (~=4.9.1)
Requires-Dist: requests (~=2.25.1)
Requires-Dist: iso8601 (~=0.1.14)
Requires-Dist: chardet (~=4.0.0)
Requires-Dist: jinja2 (~=3.0.1)
Requires-Dist: beautifulsoup4 (~=4.9.3)
Requires-Dist: mzml2isa (==1.1.1)
Requires-Dist: biopython (~=1.79)
Requires-Dist: progressbar2 (~=3.53.1)
Requires-Dist: deepdiff (~=5.5.0)
Requires-Dist: PyYAML (~=5.4.1)
Requires-Dist: bokeh (~=2.3.2)
Requires-Dist: certifi (==2021.5.30)
Requires-Dist: flake8 (==3.9.2)
Requires-Dist: ddt (==1.4.2)
Requires-Dist: behave (==1.2.6)
Requires-Dist: httpretty (==1.1.3)
Requires-Dist: sure (==2.0.0)
Requires-Dist: coveralls (~=3.1.0)
Requires-Dist: rdflib (~=6.0.2)
Requires-Dist: Flask (~=2.2.2)
Requires-Dist: flask-sqlalchemy (~=3.0.2)
